{"cameraMode":{"drawMode":0,"name":"Shaded","section":"Shading Mode"},"sceneLighting":true,"audioPlay":false,"sceneViewState":{"showFog":true,"showMaterialUpdate":false,"showSkybox":true,"showFlares":true,"showImageEffects":true,"showParticleSystems":true},"in2DMode":false,"pivot":{"x":231.0999755859375,"y":245.3300018310547,"z":0.000015258790881489404},"rotation":{"x":0.004508469253778458,"y":0.00907217338681221,"z":0.00051223358605057,"w":1.0000542402267457},"size":343.1309814453125,"orthographic":false}